CHANGES.txt
LICENSE.txt
MANIFEST.in
README.txt
setup.py
Propeller.egg-info/PKG-INFO
Propeller.egg-info/SOURCES.txt
Propeller.egg-info/dependency_links.txt
Propeller.egg-info/requires.txt
Propeller.egg-info/top_level.txt
docs/_build/html/_sources/application-object.txt
docs/_build/html/_sources/hello-world.txt
docs/_build/html/_sources/index.txt
docs/_build/html/_sources/installation.txt
docs/_build/html/_sources/introduction.txt
docs/_build/html/_sources/request-handlers.txt
docs/_build/html/_sources/request-object.txt
propeller/__init__.py
propeller/app.py
propeller/cookie.py
propeller/loop.py
propeller/multipart.py
propeller/options.py
propeller/reloader.py
propeller/request.py
propeller/request_handler.py
propeller/response.py
propeller/template.py
propeller/uploaded_file.py
propeller/templates/error.html
propeller/util/__init__.py
propeller/util/dict.py
test/test_cookie.py
test/test_multipart.py
test/test_request.py
test/test_response.py
test/test_static_file_handler.py
test/test_template.py
test/test_util_dict.py