Metadata-Version: 1.0
Name: Propeller
Version: 0.1.6
Summary: A lightweight HTTP framework written in Python
Home-page: http://www.propellerframework.org/
Author: Bas Wind
Author-email: mailtobwind@gmail.com
License: LICENSE.txt
Download-URL: https://pypi.python.org/pypi/Propeller
Keywords: web server http framework fast
Platform: UNKNOWN
